tests/__init__.py
tests/test_module1.py
zpypro/__init__.py
zpypro/logging_config.yaml
zpypro/main.py
zpypro/module1.py
zpypro-0.1.0.dist-info/LICENSE
zpypro-0.1.0.dist-info/METADATA
zpypro-0.1.0.dist-info/WHEEL
zpypro-0.1.0.dist-info/entry_points.txt
zpypro-0.1.0.dist-info/top_level.txt
zpypro-0.1.0.dist-info/RECORD
