Metadata-Version: 2.1
Name: zpypro
Version: 0.1.0
Summary: A python project template.
Home-page: https://github.com/you-zhou/zpypro
Author: You Zhou
Author-email: zhouyou.xy@gmail.com
Classifier: Programming Language :: Python :: 3
Classifier: License :: OSI Approved :: MIT License
Classifier: Operating System :: OS Independent
Requires-Python: >=3.6
License-File: LICENSE
